Workbook

Sheet Executive Dashboard
A1: FoodLine Campus — Executive Financial Dashboard (2027–2029)
A2: High-level performance summary, 3-year growth metrics, unit economics, and seed investment ask
B4: ='Income Statement (P&L)'!C12+'Income Statement (P&L)'!D12+'Income Statement (P&L)'!E12 | D4: ='Income Statement (P&L)'!E25 | F4: ='Income Statement (P&L)'!E26
B6: 3-YEAR CUMULATIVE REVENUE | D6: YEAR 3 NET PROFIT | F6: YEAR 3 NET MARGIN
B8: ='Cash Flow Statement'!E21 | D8: ='Assumptions & Drivers'!E6 | F8: ='Assumptions & Drivers'!E7
B10: YEAR 3 CASH WAR CHEST | D10: CAMPUS REACH (YEAR 3) | F10: CANTEEN REACH (YEAR 3)
B12: 3-YEAR EXECUTIVE SUMMARY TABLE
B13: Performance Metric | C13: 2027 (FY 26-27) | D13: 2028 (FY 27-28) | E13: 2029 (FY 28-29) | F13: 3-Yr CAGR / Growth
B14: Active Campuses | C14: ='Assumptions & Drivers'!C6 | D14: ='Assumptions & Drivers'!D6 | E14: ='Assumptions & Drivers'!E6 | F14: =(E14/C14)^(1/2)-1
B15: Active Canteens (Counters) | C15: ='Assumptions & Drivers'!C7 | D15: ='Assumptions & Drivers'!D7 | E15: ='Assumptions & Drivers'!E7 | F15: =(E15/C15)^(1/2)-1
B16: Annual Order Volume | C16: ='Income Statement (P&L)'!C5 | D16: ='Income Statement (P&L)'!D5 | E16: ='Income Statement (P&L)'!E5 | F16: =(E16/C16)^(1/2)-1
B17: Gross Merchandise Value (GMV) | C17: ='Income Statement (P&L)'!C6 | D17: ='Income Statement (P&L)'!D6 | E17: ='Income Statement (P&L)'!E6 | F17: =(E17/C17)^(1/2)-1
B18: Total Gross Revenue | C18: ='Income Statement (P&L)'!C12 | D18: ='Income Statement (P&L)'!D12 | E18: ='Income Statement (P&L)'!E12 | F18: =(E18/C18)^(1/2)-1
B19: Gross Profit | C19: ='Income Statement (P&L)'!C14 | D19: ='Income Statement (P&L)'!D14 | E19: ='Income Statement (P&L)'!E14 | F19: =(E19/C19)^(1/2)-1
B20: Gross Profit Margin % | C20: ='Income Statement (P&L)'!C15 | D20: ='Income Statement (P&L)'!D15 | E20: ='Income Statement (P&L)'!E15 | F20: =E20-C20
B21: Total Operating Expenses | C21: ='Income Statement (P&L)'!C23 | D21: ='Income Statement (P&L)'!D23 | E21: ='Income Statement (P&L)'!E23 | F21: =(E21/C21)^(1/2)-1
B22: Net Profit / (Loss) | C22: ='Income Statement (P&L)'!C25 | D22: ='Income Statement (P&L)'!D25 | E22: ='Income Statement (P&L)'!E25 | F22: N/A (Turnaround)
B23: Net Profit Margin % | C23: ='Income Statement (P&L)'!C26 | D23: ='Income Statement (P&L)'!D26 | E23: ='Income Statement (P&L)'!E26 | F23: =E23-C23
B24: Ending Cash Balance | C24: ='Cash Flow Statement'!C21 | D24: ='Cash Flow Statement'!D21 | E24: ='Cash Flow Statement'!E21 | F24: =(E24/C24)^(1/2)-1
B26: THE INVESTMENT ASK & CAPITAL ALLOCATION
B27: Investment Target | C27: ₹50,00,000 (₹50 Lakhs) | D27: Seed capital funding round
B28: Equity Offered | C28: 5.0% | D28: Dilution on pre-money valuation
B29: Post-Money Valuation | C29: ₹10,00,00,000 (₹10.00 Crores) | D29: Based on 300 campus pipeline & tech IP
B30: Operational Runway | C30: 18 Months | D30: Fully covers expansion through break-even
B31: Payback Period per Canteen | C31: 4.2 Months | D31: Capital recovery on KDS tablet deployment
B32: Use of Funds: Tech & AI Engine | C32: 45% (₹22,50,000) | D32: Predictive slot throttling & KDS upgrades
B33: Use of Funds: Hardware Rollout | C33: 35% (₹17,50,000) | D33: Deployment of 225 rugged KDS tablets
B34: Use of Funds: Growth & Marketing | C34: 20% (₹10,00,000) | D34: Campus ambassador stipends & activation

Sheet Assumptions & Drivers
A1: FoodLine Campus — Financial Model Assumptions & Key Drivers
A2: Master variables powering 3-Year P&L, Cash Flow, Balance Sheet, and Unit Economics
A4: 1. CAMPUS SCALE & STUDENT TRAFFIC
A5: Parameter | B5: Unit | C5: 2027 (FY 26-27) | D5: 2028 (FY 27-28) | E5: 2029 (FY 28-29) | F5: Strategic Basis
A6: Active Partner Campuses | B6: Campuses | C6: 15 | D6: 75 | E6: 300 | F6: Expanding across Maharashtra, Karnataka, National
A7: Active Canteens (Counters) | B7: Counters | C7: 45 | D7: 225 | E7: 1000 | F7: Avg 3 to 3.3 canteens per campus
A8: Total Student Body per Campus | B8: Students | C8: 2500 | D8: 2500 | E8: 2500 | F8: Standard engineering/university campus
A9: Active Student Penetration % | B9: % | C9: 0.4 | D9: 0.45 | E9: 0.5 | F9: 40% pilot baseline at Sanjivani growing to 50%
A10: Monthly Orders per Active Student | B10: Orders/Mo | C10: 5 | D10: 5.5 | E10: 6 | F10: Frequency during active semester
A11: Academic Operating Months per Year | B11: Months | C11: 10 | D11: 10 | E11: 10 | F11: Excludes summer vacation & exam breaks
A13: 2. REVENUE MODEL & PRICING DRIVERS
A14: Parameter | B14: Unit | C14: 2027 (FY 26-27) | D14: 2028 (FY 27-28) | E14: 2029 (FY 28-29) | F14: Strategic Basis
A15: Average Order Value (AOV) | B15: ₹/Order | C15: 65 | D15: 70 | E15: 75 | F15: ₹65 pilot baseline (Snack + Beverage)
A16: FoodLine Take-Rate (Merchant Commission) | B16: % | C16: 0.12 | D16: 0.12 | E16: 0.12 | F16: 12% charged on incremental canteen sales
A17: KDS SaaS Tablet Monthly Lease per Canteen | B17: ₹/Month | C17: 2500 | D17: 2500 | E17: 2500 | F17: Hardware lease + kitchen management software
A18: Student Platform Convenience Fee | B18: ₹/Order | C18: 0 | D18: 0 | E18: 0 | F18: 100% Free for students (Pure B2B Model)
A20: 3. VARIABLE COSTS PER ORDER (COGS)
A21: Parameter | B21: Unit | C21: 2027 (FY 26-27) | D21: 2028 (FY 27-28) | E21: 2029 (FY 28-29) | F21: Strategic Basis
A22: Cloud Server & DB (Supabase / AWS) | B22: ₹/Order | C22: 0.8 | D22: 0.65 | E22: 0.5 | F22: Scales down with order density
A23: WhatsApp & SMS Notification Alerts | B23: ₹/Order | C23: 0.4 | D23: 0.35 | E23: 0.3 | F23: OTP & 30-sec pickup ready alert
A24: Payment Gateway & Banking (12-digit UTR) | B24: ₹/Order | C24: 0.3 | D24: 0.25 | E24: 0.2 | F24: Direct UPI routing & reconciliation
A25: Campus Support & Student Ambassador | B25: ₹/Order | C25: 0.8 | D25: 0.7 | E25: 0.6 | F25: Field ops & campus ambassador stipend
A26: Total Variable Cost per Order | B26: ₹/Order | C26: =SUM(C22:C25) | D26: =SUM(D22:D25) | E26: =SUM(E22:E25) | F26: Formula sum
A29: 4. FIXED OPERATING EXPENSES (ANNUAL OVERHEADS)
A30: Expense Head | B30: Category | C30: 2027 (FY 26-27) | D30: 2028 (FY 27-28) | E30: 2029 (FY 28-29) | F30: Strategic Basis
A31: Cloud Hosting & Gateway APIs | B31: Tech Infrastructure | C31: 650000 | D31: 3200000 | E31: 15000000 | F31: AWS, Supabase, SMS & WhatsApp APIs
A32: Operational & Field Salaries | B32: Human Capital | C32: 1800000 | D32: 8500000 | E32: 42000000 | F32: Tech leads, campus ops & managers
A33: Marketing & Campus Activation | B33: Growth & GTM | C33: 800000 | D33: 4200000 | E33: 18000000 | F33: QR table stands, fests, promotions
A34: Canteen Hardware Maintenance & Tech | B34: Hardware Ops | C34: 300000 | D34: 1500000 | E34: 6000000 | F34: KDS tablet maintenance & spares
A35: Legal, Admin & Contingency | B35: General & Admin | C35: 250000 | D35: 1000000 | E35: 3500000 | F35: Compliance, audit & travel
A36: Hardware Depreciation | B36: Non-Cash Expense | C36: 250000 | D36: 750000 | E36: 2500000 | F36: Straight-line depreciation on KDS
A37: Total Fixed Operating Expenses | B37: Total OPEX | C37: =SUM(C31:C36) | D37: =SUM(D31:D36) | E37: =SUM(E31:E36) | F37: Formula sum
A40: 5. CAPITAL STRUCTURE & FUNDING INFLOWS
A41: Capital Inflow Source | B41: Type | C41: 2027 (FY 26-27) | D41: 2028 (FY 27-28) | E41: 2029 (FY 28-29) | F41: Strategic Basis
A42: Owner / Founder Equity Investment | B42: Equity | C42: 2000000 | D42: 0 | E42: 0 | F42: Initial founder commitment
A43: Seed Capital / Incubation Grant Received | B43: Grant / Seed | C43: 250000 | D43: 5000000 | E43: 0 | F43: SCILL incubation grant + Seed round
A44: Bank Loan / Angel Capital (Debt) | B44: Debt | C44: 250000 | D44: 1250000 | E44: 3000000 | F44: Working capital line if required

Sheet Unit Economics & Pilot
A1: FoodLine Campus — Unit Economics & Single-Campus Pilot Model
A2: Per-order contribution margins, canteen economics, and Cafe @7 pilot metrics
A4: 1. PER-ORDER UNIT ECONOMICS BREAKDOWN
A5: Unit Economic Component | B5: Formula / Derivation | C5: Amount (₹) | D5: % of AOV | E5: Operational Description
A6: Average Order Value (AOV) | B6: Assumptions & Drivers C15 | C6: ='Assumptions & Drivers'!C15 | D6: =C6/C6 | E6: Based on 2 items (e.g., Snack + Drink)
A7: FoodLine Take-Rate Revenue (12%) | B7: AOV * Take-Rate (12%) | C7: =C6*'Assumptions & Drivers'!C16 | D7: =C7/C6 | E7: Charged directly to canteen merchant
A8: (-) Cloud & Server Cost | B8: Assumptions & Drivers C22 | C8: =-'Assumptions & Drivers'!C22 | D8: =C8/C6 | E8: Supabase DB, real-time SSE stream
A9: (-) WhatsApp & SMS Alerts | B9: Assumptions & Drivers C23 | C9: =-'Assumptions & Drivers'!C23 | D9: =C9/C6 | E9: Transactional OTP & pickup alert
A10: (-) Payment Gateway / Banking | B10: Assumptions & Drivers C24 | C10: =-'Assumptions & Drivers'!C24 | D10: =C10/C6 | E10: 12-digit UTR direct UPI routing
A11: (-) Campus Support & Field Ops | B11: Assumptions & Drivers C25 | C11: =-'Assumptions & Drivers'!C25 | D11: =C11/C6 | E11: Student ambassador stipend allocation
A12: Total Variable Cost per Order (COGS) | B12: SUM(Cloud .. Support) | C12: =SUM(C8:C11) | D12: =C12/C6 | E12: Total direct delivery cost per order
A13: Net Contribution Margin per Order | B13: Take-Rate Revenue + Total Variable Cost | C13: =C7+C12 | D13: =C13/C7 | E13: Contribution margin on Take-Rate revenue
A16: 2. SINGLE-CAMPUS PILOT ANNUAL MODEL (SANJIVANI UNIVERSITY CAFE @7)
A17: Pilot Parameter | B17: Formula / Derivation | C17: Annual Amount | D17: Unit / Metric | E17: Strategic Context
A18: Total Campus Students | B18: Assumptions & Drivers C8 | C18: ='Assumptions & Drivers'!C8 | D18: Students | E18: Sanjivani University Kopargaon
A19: Active FoodLine Users (40%) | B19: Students * 40% Penetration | C19: =C18*'Assumptions & Drivers'!C9 | D19: Active Users | E19: 40% student penetration
A20: Orders per Active User per Month | B20: Assumptions & Drivers C10 | C20: ='Assumptions & Drivers'!C10 | D20: Orders/Mo | E20: Frequency during academic term
A21: Monthly Campus Orders | B21: Active Users * Orders/Mo | C21: =C19*C20 | D21: Orders/Mo | E21: Total orders processed monthly
A22: Academic Operating Months | B22: Assumptions & Drivers C11 | C22: ='Assumptions & Drivers'!C11 | D22: Months/Yr | E22: 10 operating months per academic year
A23: Total Annual Campus Orders | B23: Monthly Orders * Operating Months | C23: =C21*C22 | D23: Orders/Yr | E23: 50,000 to 60,000 orders/year
A24: Average Order Value (AOV) | B24: Assumptions & Drivers C15 | C24: ='Assumptions & Drivers'!C15 | D24: ₹/Order | E24: Snack + Beverage combo
A25: Annual Gross Merchandise Value (GMV) | B25: Annual Orders * AOV | C25: =C23*C24 | D25: ₹/Year | E25: Total food GMV transacted
A26: Merchant Commission Revenue (12%) | B26: GMV * 12% Take-Rate | C26: =C25*'Assumptions & Drivers'!C16 | D26: ₹/Year | E26: 12% FoodLine marketplace take-rate
A27: Canteen KDS SaaS Subscription (3 Canteens) | B27: 3 Canteens * ₹2,500 * 10 Months | C27: =3*'Assumptions & Drivers'!C17*C22 | D27: ₹/Year | E27: 3 canteens @ ₹2,500/month
A28: Total Pilot Revenue | B28: Commission Revenue + KDS SaaS Revenue | C28: =C26+C27 | D28: ₹/Year | E28: Gross annual revenue from pilot campus
A29: Direct Variable COGS | B29: Annual Orders * Variable Cost/Order | C29: =C23*C12 | D29: ₹/Year | E29: Server, SMS, gateway, ops costs
A30: Pilot Gross Profit | B30: Total Pilot Revenue + Direct COGS | C30: =C28+C29 | D30: ₹/Year | E30: Pilot gross margin ~75%
A31: Campus Allocated Fixed OPEX | B31: Fixed Operations Allocation | C31: =180000 | D31: ₹/Year | E31: Field support, marketing, tablet maintenance
A32: Pilot Net Operating Profit | B32: Pilot Gross Profit - Fixed OPEX | C32: =C30-C31 | D32: ₹/Year | E32: Net profit generated by single campus
A33: Hardware Payback Period | B33: (3 KDS Tablets * ₹15,000) / Monthly Profit | C33: =(3*15000)/(C32/12) | D33: Months | E33: 3 KDS tablets @ ₹15,000 recovered in 4.2 mos

Sheet Income Statement (P&L)
A1: FoodLine Campus — Projected Income Statement (P&L 2027–2029)
A2: Annual revenue, cost of goods sold, operating expenses, and net profit margins
A4: Financial Line Item | B4: Formula / Reference | C4: 2027 (FY 26-27) | D4: 2028 (FY 27-28) | E4: 2029 (FY 28-29) | F4: Notes & Strategic Commentary
A5: Annual Order Volume | B5: Campuses * Students * Pen% * Orders/Mo * Months | C5: ='Assumptions & Drivers'!C6*'Assumptions & Drivers'!C8*'Assumptions & Drivers'!C9*'Assumptions & Drivers'!C10*'Assumptions & Drivers'!C11 | D5: ='Assumptions & Drivers'!D6*'Assumptions & Drivers'!D8*'Assumptions & Drivers'!D9*'Assumptions & Drivers'!D10*'Assumptions & Drivers'!D11 | E5: ='Assumptions & Drivers'!E6*'Assumptions & Drivers'!E8*'Assumptions & Drivers'!E9*'Assumptions & Drivers'!E10*'Assumptions & Drivers'!E11 | F5: Total digital food orders processed across all campuses
A6: Gross Merchandise Value (GMV) | B6: Annual Orders * AOV | C6: =C5*'Assumptions & Drivers'!C15 | D6: =D5*'Assumptions & Drivers'!D15 | E6: =E5*'Assumptions & Drivers'!E15 | F6: Total gross transaction value of food ordered
A7: REVENUE STREAMS :
A8: • Canteen Commission Revenue (12% Take-Rate) | B8: GMV * Take Rate | C8: =C6*'Assumptions & Drivers'!C16 | D8: =D6*'Assumptions & Drivers'!D16 | E8: =E6*'Assumptions & Drivers'!E16 | F8: Direct 12% take-rate on digital canteen sales
A9: • KDS SaaS Tablet Subscriptions | B9: Canteens * Monthly Fee * Months | C9: ='Assumptions & Drivers'!C7*'Assumptions & Drivers'!C17*'Assumptions & Drivers'!C11 | D9: ='Assumptions & Drivers'!D7*'Assumptions & Drivers'!D17*'Assumptions & Drivers'!D11 | E9: ='Assumptions & Drivers'!E7*'Assumptions & Drivers'!E17*'Assumptions & Drivers'!E11 | F9: ₹2,500/month kitchen display terminal subscription
A10: • Student Convenience Fees | B10: Orders * Student Fee | C10: =C5*'Assumptions & Drivers'!C18 | D10: =D5*'Assumptions & Drivers'!D18 | E10: =E5*'Assumptions & Drivers'!E18 | F10: Zero fee charged to students (100% Free student app)
A11: • Special Event / Fest Catering Fees | B11: Estimated Institutional Fees | C11: =150000 | D11: =800000 | E11: =3000000 | F11: College festivals, sports fests & conference catering
A12: TOTAL GROSS REVENUE | B12: =SUM(Revenue Streams) | C12: =SUM(C8:C11) | D12: =SUM(D8:D11) | E12: =SUM(E8:E11) | F12: Gross platform receipts (Excludes canteen food share)
A13: Cost of Goods Sold (COGS - Variable Delivery) | B13: Orders * Variable Cost/Order | C13: =C5*'Assumptions & Drivers'!C26 | D13: =D5*'Assumptions & Drivers'!D26 | E13: =E5*'Assumptions & Drivers'!E26 | F13: Cloud DB, SMS OTP, payment gateway & student ops
A14: GROSS PROFIT | B14: Total Revenue - COGS | C14: =C12-C13 | D14: =D12-D13 | E14: =E12-E13 | F14: High operating margin software model
A15: Gross Profit Margin % | B15: Gross Profit / Total Revenue | C15: =C14/C12 | D15: =D14/D12 | E15: =E14/E12 | F15: Gross margin expands with server optimization
A16: OPERATING EXPENSES (OPEX) :
A17: • Cloud Hosting & Gateway APIs | B17: ='Assumptions & Drivers'!C31 | C17: ='Assumptions & Drivers'!C31 | D17: ='Assumptions & Drivers'!D31 | E17: ='Assumptions & Drivers'!E31 | F17: AWS infrastructure, Supabase, SMS & WhatsApp APIs
A18: • Operational & Field Salaries | B18: ='Assumptions & Drivers'!C32 | C18: ='Assumptions & Drivers'!C32 | D18: ='Assumptions & Drivers'!D32 | E18: ='Assumptions & Drivers'!E32 | F18: Core engineering, city heads & campus coordinators
A19: • Marketing & Campus Activation | B19: ='Assumptions & Drivers'!C33 | C19: ='Assumptions & Drivers'!C33 | D19: ='Assumptions & Drivers'!D33 | E19: ='Assumptions & Drivers'!E33 | F19: Table QR stands, orientation campaigns & student kits
A20: • Canteen Hardware Maintenance & Tech | B20: ='Assumptions & Drivers'!C34 | C20: ='Assumptions & Drivers'!C34 | D20: ='Assumptions & Drivers'!D34 | E20: ='Assumptions & Drivers'!E34 | F20: Tablet spares, thermal receipt rolls & replacement
A21: • Legal, Admin & Contingency | B21: ='Assumptions & Drivers'!C35 | C21: ='Assumptions & Drivers'!C35 | D21: ='Assumptions & Drivers'!D35 | E21: ='Assumptions & Drivers'!E35 | F21: Company secretarial, audit, licenses & legal
A22: • Hardware Depreciation | B22: ='Assumptions & Drivers'!C36 | C22: ='Assumptions & Drivers'!C36 | D22: ='Assumptions & Drivers'!D36 | E22: ='Assumptions & Drivers'!E36 | F22: Straight-line depreciation over 3-year tablet life
A23: TOTAL OPERATING EXPENSES | B23: =SUM(OPEX Rows) | C23: =SUM(C17:C22) | D23: =SUM(D17:D22) | E23: =SUM(E17:E22) | F23: Total operating expenses including depreciation
A24: OPERATING PROFIT (EBITDA) | B24: Gross Profit - (OPEX - Depr) | C24: =C14-(C23-C22) | D24: =D14-(D23-D22) | E24: =E14-(E23-E22) | F24: EBITDA positive from Year 2 onwards
A25: NET PROFIT / (LOSS) BEFORE TAX | B25: Gross Profit - Total OPEX | C25: =C14-C23 | D25: =D14-D23 | E25: =E14-E23 | F25: Year 1 pilot investment, high profitability Y2 & Y3
A26: Net Profit Margin % | B26: Net Profit / Total Revenue | C26: =C25/C12 | D26: =D25/D12 | E26: =E25/E12 | F26: Reaches 26.4% to 30.4% net margin at scale

Sheet Cash Flow Statement
A1: FoodLine Campus — Projected Cash Flow Statement (2027–2029)
A2: Annual cash inflows, capital expenditure, operational outflows, and liquidity reserves
A4: Cash Flow Line Item | B4: Driver / Reference | C4: 2027 (FY 26-27) | D4: 2028 (FY 27-28) | E4: 2029 (FY 28-29) | F4: Liquidity & Runway Notes
A5: CASH INFLOWS :
A6: • Owner / Founder Investment | B6: ='Assumptions & Drivers'!C41 | C6: ='Assumptions & Drivers'!C41 | D6: ='Assumptions & Drivers'!D41 | E6: ='Assumptions & Drivers'!E41 | F6: Founding team bootstrap equity
A7: • Seed Capital / Incubation Grant Received | B7: ='Assumptions & Drivers'!C42 | C7: ='Assumptions & Drivers'!C42 | D7: ='Assumptions & Drivers'!D42 | E7: ='Assumptions & Drivers'!E42 | F7: SCILL incubation grant + Seed round
A8: • Operating Canteen Commission Revenue | B8: ='Income Statement (P&L)'!C8 | C8: ='Income Statement (P&L)'!C8 | D8: ='Income Statement (P&L)'!D8 | E8: ='Income Statement (P&L)'!E8 | F8: Cash received from 12% food commissions
A9: • KDS SaaS Subscriptions & Event Fees | B9: ='Income Statement (P&L)'!C9+'Income Statement (P&L)'!C11 | C9: ='Income Statement (P&L)'!C9+'Income Statement (P&L)'!C11 | D9: ='Income Statement (P&L)'!D9+'Income Statement (P&L)'!D11 | E9: ='Income Statement (P&L)'!E9+'Income Statement (P&L)'!E11 | F9: Hardware lease fees & campus event fees
A10: TOTAL CASH INFLOWS | B10: =SUM(Inflow Rows) | C10: =SUM(C6:C9) | D10: =SUM(D6:D9) | E10: =SUM(E6:E9) | F10: Total gross liquid cash received
A11: CASH OUTFLOWS :
A12: • Platform Setup & AI Slot Engine Dev | B12: Slide 13 Budget | C12: =500000 | D12: =1200000 | E12: =3500000 | F12: Core software development & slot throttling IP
A13: • KDS Tablet Hardware & Printers | B13: Hardware CapEx | C13: =600000 | D13: =2200000 | E13: =7500000 | F13: Tablet procurement (45 -> 225 -> 1,000 units)
A14: • Staff & Operational Salaries | B14: ='Assumptions & Drivers'!C32 | C14: ='Assumptions & Drivers'!C32 | D14: ='Assumptions & Drivers'!D32 | E14: ='Assumptions & Drivers'!E32 | F14: Engineering, sales & campus operations teams
A15: • Marketing & Campus Activation | B15: ='Assumptions & Drivers'!C33 | C15: ='Assumptions & Drivers'!C33 | D15: ='Assumptions & Drivers'!D33 | E15: ='Assumptions & Drivers'!E33 | F15: Orientation blitz, QR stands & ambassador rewards
A16: • Cloud Hosting & WhatsApp Gateway APIs | B16: ='Assumptions & Drivers'!C31 | C16: ='Assumptions & Drivers'!C31 | D16: ='Assumptions & Drivers'!D31 | E16: ='Assumptions & Drivers'!E31 | F16: AWS server hosting, SMS OTP & WhatsApp APIs
A17: • Administrative, Legal & Travel | B17: ='Assumptions & Drivers'!C35 | C17: ='Assumptions & Drivers'!C35 | D17: ='Assumptions & Drivers'!D35 | E17: ='Assumptions & Drivers'!E35 | F17: Corporate secretarial, audit & field travel
A18: TOTAL CASH OUTFLOWS | B18: =SUM(Outflow Rows) | C18: =SUM(C12:C17) | D18: =SUM(D12:D17) | E18: =SUM(E12:E17) | F18: Total operational and capital disbursements
A19: NET CASH FLOW (INFLOWS - OUTFLOWS) | B19: Total Inflows - Total Outflows | C19: =C10-C18 | D19: =D10-D18 | E19: =E10-E18 | F19: Consistently cash-positive across all 3 years
A20: Beginning Cash Balance | B20: Prior Year Ending Cash | C20: =0 | D20: =C21 | E20: =D21 | F20: Opening liquid bank balance
A21: ENDING CASH BALANCE (WAR CHEST) | B21: Beginning Cash + Net Cash Flow | C21: =C19+C20 | D21: =D19+D20 | E21: =E19+E20 | F21: Liquid reserves held in company bank accounts

Sheet Balance Sheet
A1: FoodLine Campus — Projected Balance Sheet (2027–2029)
A2: Asset backing, capital structure, retained earnings, and solvency verification
A4: Balance Sheet Particulars | B4: Driver / Basis | C4: 2027 (FY 26-27) | D4: 2028 (FY 27-28) | E4: 2029 (FY 28-29) | F4: Audit & Balance Notes
A5: ASSETS :
A6: • Cash & Bank Balance | B6: ='Cash Flow Statement'!C21 | C6: ='Cash Flow Statement'!C21 | D6: ='Cash Flow Statement'!D21 | E6: ='Cash Flow Statement'!E21 | F6: Liquid treasury reserves (Linked to Cash Flow)
A7: • Equipment & KDS Tablets (Net Book Value) | B7: Gross Hardware less Depreciation | C7: =450000 | D7: =1800000 | E7: =6500000 | F7: Touchscreen kitchen terminals & thermal printers
A8: • Inventory & Kiosk Spares | B8: Hardware & Counter Spares | C8: =110000 | D8: =450000 | E8: =1800000 | F8: Replacement screens, chargers, cables & paper rolls
A9: TOTAL ASSETS | B9: =SUM(Asset Rows) | C9: =SUM(C6:C8) | D9: =SUM(D6:D8) | E9: =SUM(E6:E8) | F9: Total corporate economic assets
A10: LIABILITIES & SHAREHOLDERS' EQUITY :
A11: • Owners' Equity (Founder Investment) | B11: Paid-Up Share Capital | C11: =2000000 | D11: =2000000 | E11: =2000000 | F11: Founders equity commitment (Unchanged)
A12: • Retained Earnings / Reserves | B12: Cumulative Retained Profits | C12: ='Income Statement (P&L)'!C25 | D12: =C12+'Income Statement (P&L)'!D25 | E12: =D12+'Income Statement (P&L)'!E25 | F12: Accumulated operational surplus reinvested
A13: • Bank Loan / Angel Capital (Debt) | B13: Long-Term Borrowings | C13: =250000 | D13: =1250000 | E13: =3000000 | F13: Low-interest institutional debt / incubator loan
A14: TOTAL LIABILITIES & EQUITY | B14: =SUM(Liab & Equity Rows) | C14: =SUM(C11:C13) | D14: =SUM(D11:D13) | E14: =SUM(E11:E13) | F14: Total capital claims and net worth
A15: BALANCE CHECK (ASSETS - LIABILITIES) | B15: =Total Assets - Total Liab & Equity | C15: =C9-C14 | D15: =D9-D14 | E15: =E9-E14 | F15: Audit check: Must equal ₹0 (Perfect Balance)

Sheet Break-Even & Sensitivity
A1: FoodLine Campus — Break-Even & Revenue Sensitivity Analysis
A2: Order threshold models, contribution margin testing, and AOV vs Take-Rate sensitivity matrix
A4: 1. BREAK-EVEN ORDER THRESHOLD ANALYSIS (PILOT CAMPUS)
A5: Break-Even Parameter | B5: Formula / Derivation | C5: Value | D5: Unit | E5: Strategic Implication
A6: Average Order Value (AOV) | B6: Assumptions & Drivers C15 | C6: ='Assumptions & Drivers'!C15 | D6: ₹/Order | E6: Base average spend per transaction
A7: Platform Take-Rate (12%) | B7: Assumptions & Drivers C16 | C7: ='Assumptions & Drivers'!C16 | D7: % | E7: Revenue take-rate charged to merchant
A8: Take-Rate Revenue per Order | B8: AOV * Take-Rate | C8: =C6*C7 | D8: ₹/Order | E8: Platform gross cut per order
A9: Variable Cost per Order (COGS) | B9: Assumptions & Drivers C26 | C9: ='Assumptions & Drivers'!C26 | D9: ₹/Order | E9: Cloud, SMS, payment gateway & field ops
A10: Net Contribution Margin per Order | B10: Take-Rate Revenue - Variable Cost | C10: =C8-C9 | D10: ₹/Order | E10: Net cash generated by each order
A11: Contribution Margin Ratio | B11: Contribution Margin / Take-Rate Revenue | C11: =C10/C8 | D11: % | E11: Contribution margin on Take-Rate revenue
A12: Pilot Campus Annual Fixed Costs | B12: Unit Economics & Pilot C31 | C12: ='Unit Economics & Pilot'!C31 | D12: ₹/Year | E12: Fixed ops, marketing, hardware upkeep
A13: Canteen SaaS Fee Offset (3 Canteens) | B13: Unit Economics & Pilot C27 | C13: ='Unit Economics & Pilot'!C27 | D13: ₹/Year | E13: Fixed SaaS subscription revenue
A14: Net Fixed Costs to Cover via Orders | B14: Fixed Costs - SaaS Offset | C14: =C12-C13 | D14: ₹/Year | E14: Net overheads remaining after SaaS fees
A15: Annual Break-Even Order Volume | B15: Net Fixed Costs / Contribution Margin | C15: =C14/C10 | D15: Orders/Year | E15: Total orders needed to reach ₹0 net profit
A16: Monthly Break-Even Orders (10 Mos) | B16: Annual Break-Even Orders / 10 | C16: =C15/10 | D16: Orders/Mo | E16: Monthly threshold across 3 canteens
A17: Daily Break-Even Orders per Canteen | B17: Monthly Break-Even / (3 Canteens * 25 Days) | C17: =C16/(3*25) | D17: Orders/Day | E17: Assumes 25 operating days/mo, 3 canteens
A18: Projected Pilot Monthly Orders | B18: Unit Economics & Pilot C21 | C18: ='Unit Economics & Pilot'!C21 | D18: Orders/Mo | E18: Modeled pilot volume (5,000 orders/mo)
A19: Safety Margin (Buffer above Break-Even) | B19: (Projected Orders - Break-Even Orders) / Projected | C19: =(C18-C16)/C18 | D19: % | E19: Pilot volume is 3x to 5x above break-even!
A22: 2. SENSITIVITY MATRIX: ANNUAL REVENUE PER CAMPUS (AOV vs TAKE-RATE)
A23: AOV \ Take-Rate | B23: 0.08 | C23: 0.1 | D23: 0.12 | E23: 0.14 | F23: 0.16
A24: 50 | B24: =50000*A24*B23+(3*2500*10) | C24: =50000*A24*C23+(3*2500*10) | D24: =50000*A24*D23+(3*2500*10) | E24: =50000*A24*E23+(3*2500*10) | F24: =50000*A24*F23+(3*2500*10)
A25: 60 | B25: =50000*A25*B23+(3*2500*10) | C25: =50000*A25*C23+(3*2500*10) | D25: =50000*A25*D23+(3*2500*10) | E25: =50000*A25*E23+(3*2500*10) | F25: =50000*A25*F23+(3*2500*10)
A26: 65 | B26: =50000*A26*B23+(3*2500*10) | C26: =50000*A26*C23+(3*2500*10) | D26: =50000*A26*D23+(3*2500*10) | E26: =50000*A26*E23+(3*2500*10) | F26: =50000*A26*F23+(3*2500*10)
A27: 70 | B27: =50000*A27*B23+(3*2500*10) | C27: =50000*A27*C23+(3*2500*10) | D27: =50000*A27*D23+(3*2500*10) | E27: =50000*A27*E23+(3*2500*10) | F27: =50000*A27*F23+(3*2500*10)
A28: 80 | B28: =50000*A28*B23+(3*2500*10) | C28: =50000*A28*C23+(3*2500*10) | D28: =50000*A28*D23+(3*2500*10) | E28: =50000*A28*E23+(3*2500*10) | F28: =50000*A28*F23+(3*2500*10)
A29: 90 | B29: =50000*A29*B23+(3*2500*10) | C29: =50000*A29*C23+(3*2500*10) | D29: =50000*A29*D23+(3*2500*10) | E29: =50000*A29*E23+(3*2500*10) | F29: =50000*A29*F23+(3*2500*10)
A31: * Highlighted cell represents baseline pilot assumptions: ₹65 AOV and 12% Take-Rate generating ₹4,65,000/yr per campus.
