Workbook

Sheet Executive Dashboard
A1: FoodLine Campus — Executive Financial Dashboard & Dynamic Model Engine
A2: 💡 ALL BLUE-HIGHLIGHTED CELLS ARE LIVE INPUTS. Change Campuses, Adoption %, Order Rates, or Goldmine Target to recalculate the entire workbook in real time!
B4: =SUM(C19:G19) | D4: =SUM(C20:G20) | F4: =G22
B6: 5-YEAR CUMULATIVE GMV | D6: 5-YEAR CUMULATIVE REVENUE | F6: YEAR 5 NET ANNUAL PROFIT
B8: ='Capital Requirements'!C11 | D8: =C22 | F8: ='Executive Dashboard'!$G$35
B10: INITIAL CAPITAL REQUIRED | D10: YEAR 1 PILOT NET PROFIT | F10: GOLDMINE 5% TARGET (ACHIEVED IN Y5)
B12: 1. 5-YEAR DYNAMIC EXPANSION MODEL (SLIDE 11)
B13: Metric | C13: Year 1 | D13: Year 2 | E13: Year 3 | F13: Year 4 | G13: Year 5 | H13: 5-Year Total / CAGR
B14: Active Campuses [EDITABLE INPUT] | C14: 1 | D14: 5 | E14: 10 | F14: 15 | G14: 20 | H14: =(G14/C14)^(1/4)-1
B15: Student Adoption Rate % [EDITABLE INPUT] | C15: 0.6 | D15: 0.6 | E15: 0.6 | F15: 0.6 | G15: 0.6 | H15: =AVERAGE(C15:G15)
B16: Active Students (Calculated) | C16: =C14*$D$29*C15 | D16: =D14*$D$29*D15 | E16: =E14*$D$29*E15 | F16: =F14*$D$29*F15 | G16: =G14*$D$29*G15 | H16: =(G16/C16)^(1/4)-1
B17: Monthly Orders / Student [EDITABLE INPUT] | C17: 20 | D17: 20 | E17: 20 | F17: 15 | G17: 15 | H17: =AVERAGE(C17:G17)
B18: Annual Orders (Calculated) | C18: =C16*(C17*$D$30) | D18: =D16*(D17*$D$30) | E18: =E16*(E17*$D$30) | F18: =F16*(F17*$D$30) | G18: =G16*(G17*$D$30) | H18: =SUM(C18:G18)
B19: Annual GMV (Gross Merchandise Value) | C19: =C18*$D$27 | D19: =D18*$D$27 | E19: =E18*$D$27 | F19: =F18*$D$27 | G19: =G18*$D$27 | H19: =SUM(C19:G19)
B20: Platform Revenue (Student Convenience Fee) | C20: =C19*$D$28 | D20: =D19*$D$28 | E20: =E19*$D$28 | F20: =F19*$D$28 | G20: =G19*$D$28 | H20: =SUM(C20:G20)
B21: Lean Annual OPEX [EDITABLE INPUT] | C21: 0 | D21: 0 | E21: 0 | F21: 0 | G21: 0 | H21: =SUM(C21:G21)
B22: NET ANNUAL PROFIT | C22: =C20-(C21+C18*$D$31) | D22: =D20-(D21+D18*$D$31) | E22: =E20-(E21+E18*$D$31) | F22: =F20-(F21+F18*$D$31) | G22: =G20-(G21+G18*$D$31) | H22: =SUM(C22:G22)
B23: Net Profit Margin % | C23: =C22/C20 | D23: =D22/D20 | E23: =E22/E20 | F23: =F22/F20 | G23: =G22/G20 | H23: =H22/H20
B25: 2. LIVE MODEL CONTROLS & MASTER DRIVERS (EDIT ANY VALUE IN BLUE)
B26: Core Operational Driver | C26: Unit | D26: Live Value [EDITABLE] | F26: Business & Valuation Parameter | G26: Live Value | H26: Strategic Implication
B27: Average Order Value (AOV) | C27: ₹/Order | D27: 70 | F27: Canteen Merchant Commission Rate | G27: 0 | H27: 100% Free for canteens (Instant merchant adoption)
B28: Student Convenience Fee Rate | C28: % | D28: 0.04 | F28: Payment Gateway MDR (Direct UPI) | G28: 0 | H28: Direct UPI peer-to-merchant rail (0% gateway fee)
B29: Total Students per Campus | C29: Students | D29: 2500 | F29: Total Initial Setup Investment | G29: ='Capital Requirements'!C11 | H29: Platform build, hardware, legal & working capital
B30: Operating Academic Months / Year | C30: Months | D30: 12 | F30: Founders Equity Commitment | G30: 0.51 | H30: Controlling stake & operational leadership
B31: Direct Variable Tech Cost / Order | C31: ₹/Order | D31: 0.3 | F31: Seed Capital / Incubation Grant | G31: =1-G30 | H31: SCILL incubation grant + Angel investor pool
F32: Target National Expansion Campuses | G32: 500 | H32: Top universities & engineering institutes in India
F33: Goldmine Total Milestone Valuation | G33: 250000000 | H33: ₹25.00 Cr (₹25,00,00,000) — User Defined Milestone Valuation
F34: Goldmine Target Allocation % | G34: 0.05 | H34: 5.0% Target Allocation requested by user
F35: Goldmine 5% Target Amount | G35: =G33*G34 | H35: ₹1,25,00,000 (₹1.25 Cr) — Achieved in Year 5 (₹1.35 Cr Net Profit)!

Sheet Assumptions & Drivers
A1: FoodLine Campus — Financial Assumptions & Model Drivers (4% Model)
A2: Master inputs driving Pilot Economics, 5-Year Growth Projections, and Viability Math
A4: 1. CAMPUS SCALE & STUDENT TRAFFIC ASSUMPTIONS
A5: Parameter | B5: Unit | C5: Year 1 | D5: Year 2 | E5: Year 3 | F5: Year 4 | G5: Year 5 | H5: Strategic Basis
A6: Active Campuses | B6: Campuses | C6: ='Executive Dashboard'!C14 | D6: ='Executive Dashboard'!D14 | E6: ='Executive Dashboard'!E14 | F6: ='Executive Dashboard'!F14 | G6: ='Executive Dashboard'!G14 | H6: Dynamically linked to Executive Dashboard
A7: Total Students per Campus | B7: Students | C7: ='Executive Dashboard'!$D$29 | D7: ='Executive Dashboard'!$D$29 | E7: ='Executive Dashboard'!$D$29 | F7: ='Executive Dashboard'!$D$29 | G7: ='Executive Dashboard'!$D$29 | H7: Dynamically linked to Executive Dashboard
A8: Active Student Penetration % | B8: % | C8: ='Executive Dashboard'!C15 | D8: ='Executive Dashboard'!D15 | E8: ='Executive Dashboard'!E15 | F8: ='Executive Dashboard'!F15 | G8: ='Executive Dashboard'!G15 | H8: Dynamically linked to Executive Dashboard (Editable per year!)
A9: Active Students per Campus | B9: Students | C9: =C7*C8 | D9: =D7*D8 | E9: =E7*E8 | F9: =F7*F8 | G9: =G7*G8 | H9: Formula: Total Students * Penetration %
A10: Total Active Students Across Network | B10: Students | C10: =C6*C9 | D10: =D6*D9 | E10: =E6*E9 | F10: =F6*F9 | G10: =G6*G9 | H10: Formula: Campuses * Active Students
A11: Monthly Orders per Active Student | B11: Orders/Mo | C11: ='Executive Dashboard'!C17 | D11: ='Executive Dashboard'!D17 | E11: ='Executive Dashboard'!E17 | F11: ='Executive Dashboard'!F17 | G11: ='Executive Dashboard'!G17 | H11: Dynamically linked to Executive Dashboard (Editable per year!)
A12: Operating Months per Year | B12: Months | C12: ='Executive Dashboard'!$D$30 | D12: ='Executive Dashboard'!$D$30 | E12: ='Executive Dashboard'!$D$30 | F12: ='Executive Dashboard'!$D$30 | G12: ='Executive Dashboard'!$D$30 | H12: Dynamically linked to Executive Dashboard
A13: Annual Orders per Active Student | B13: Orders/Yr | C13: =C11*C12 | D13: =D11*D12 | E13: =E11*E12 | F13: =F11*F12 | G13: =G11*G12 | H13: Formula: Monthly Orders * Operating Months
A16: 2. REVENUE MODEL & PRICING DRIVERS (SLIDE 7)
A17: Parameter | B17: Unit | C17: Year 1 | D17: Year 2 | E17: Year 3 | F17: Year 4 | G17: Year 5 | H17: Strategic Basis
A18: Average Order Value (AOV) | B18: ₹/Order | C18: ='Executive Dashboard'!$D$27 | D18: ='Executive Dashboard'!$D$27 | E18: ='Executive Dashboard'!$D$27 | F18: ='Executive Dashboard'!$D$27 | G18: ='Executive Dashboard'!$D$27 | H18: Dynamically linked to Executive Dashboard
A19: Student Convenience Fee Rate | B19: % | C19: ='Executive Dashboard'!$D$28 | D19: ='Executive Dashboard'!$D$28 | E19: ='Executive Dashboard'!$D$28 | F19: ='Executive Dashboard'!$D$28 | G19: ='Executive Dashboard'!$D$28 | H19: Dynamically linked to Executive Dashboard
A20: Canteen Commission Rate | B20: % | C20: ='Executive Dashboard'!$G$27 | D20: ='Executive Dashboard'!$G$27 | E20: ='Executive Dashboard'!$G$27 | F20: ='Executive Dashboard'!$G$27 | G20: ='Executive Dashboard'!$G$27 | H20: 100% Free for canteens
A21: Payment Gateway MDR (Direct UPI) | B21: % | C21: ='Executive Dashboard'!$G$28 | D21: ='Executive Dashboard'!$G$28 | E21: ='Executive Dashboard'!$G$28 | F21: ='Executive Dashboard'!$G$28 | G21: ='Executive Dashboard'!$G$28 | H21: Direct UPI rail (0% MDR)
A22: KDS Kitchen Software Fee | B22: ₹/Month | C22: 0 | D22: 0 | E22: 0 | F22: 0 | G22: 0 | H22: 100% Free KDS tablet software for canteens
A24: 3. UNIT COSTS & EXPENSES (COGS & LEAN OPEX)
A25: Parameter | B25: Unit | C25: Year 1 | D25: Year 2 | E25: Year 3 | F25: Year 4 | G25: Year 5 | H25: Strategic Basis
A26: Direct Variable Tech Cost per Order | B26: ₹/Order | C26: ='Executive Dashboard'!$D$31 | D26: ='Executive Dashboard'!$D$31 | E26: ='Executive Dashboard'!$D$31 | F26: ='Executive Dashboard'!$D$31 | G26: ='Executive Dashboard'!$D$31 | H26: SMS OTP, Supabase DB & server costs
A27: Lean Annual OPEX | B27: ₹/Year | C27: ='Executive Dashboard'!C21 | D27: ='Executive Dashboard'!D21 | E27: ='Executive Dashboard'!E21 | F27: ='Executive Dashboard'!F21 | G27: ='Executive Dashboard'!G21 | H27: Dynamically linked to Executive Dashboard
A28: Lean Monthly OPEX | B28: ₹/Month | C28: =C27/12 | D28: =D27/12 | E28: =E27/12 | F28: =F27/12 | G28: =G27/12 | H28: Monthly overhead budget per year

Sheet Single-Campus Pilot Economics
A1: FoodLine Campus — Single-Campus Pilot Unit Economics (Slide 8)
A2: 4% Student Convenience Fee Model at Sanjivani University Cafe @7 (2,500 Students)
A4: PILOT SCALE METRICS (SANJIVANI UNIVERSITY CAFE @7)
B5: ='Executive Dashboard'!$D$29 | C5: =B5*'Executive Dashboard'!C15 | D5: =C5*('Executive Dashboard'!C17*'Executive Dashboard'!$D$30) | E5: =D5*'Executive Dashboard'!$D$27
B7: TOTAL CAMPUS STUDENTS | C7: ACTIVE USERS (ADOPTION RATE) | D7: ANNUAL ORDERS (MONTHLY FREQ) | E7: ANNUAL GMV (@ AOV)
A9: PILOT ANNUAL INCOME STATEMENT (EXACT SLIDE 8 TABLE)
A10: Financial Item | B10: Derivation / Formula | C10: Annual Amount | D10: % of Revenue | E10: Strategic Context
A11: Gross Merchandise Value (GMV @ AOV) | B11: Annual Orders * AOV | C11: =E5 | D11: - | E11: Total food sales transacted through platform
A12: FoodLine Revenue (4% Student Convenience Fee) | B12: GMV * Convenience Fee % | C12: =C11*'Executive Dashboard'!$D$28 | D12: =C12/C12 | E12: Paid by students to skip 20-min wait
A13: Direct Variable Tech Cost (~₹0.30/order SMS/Server) | B13: Annual Orders * Variable Tech Cost | C13: =D5*'Executive Dashboard'!$D$31 | D13: =C13/C12 | E13: SMS OTP, Supabase real-time SSE stream
A14: Gross Profit | B14: Revenue - Variable Tech Cost | C14: =C12-C13 | D14: =C14/C12 | E14: High gross margin digital rail (>90%)
A15: Lean Campus OPEX (Hosting + Lead + Marketing) | B15: Executive Dashboard Year 1 OPEX | C15: ='Executive Dashboard'!C21 | D15: =C15/C12 | E15: Cloud hosting + campus lead stipend + QR tents
A16: NET PROFIT | B16: Gross Profit - Lean Campus OPEX | C16: =C14-C15 | D16: =C16/C12 | E16: Outstanding single-campus profitability
A19: PILOT MONTHLY RUN-RATE BREAKDOWN (12 MONTHS)
A20: Month | B20: Active Students | C20: Orders / Mo | D20: Monthly GMV (₹) | E20: Revenue (4%) | F20: Tech Cost (₹0.30) | G20: Gross Profit | H20: Monthly OPEX | I20: Monthly Net Profit
A21: Month 1 | B21: ='Single-Campus Pilot Economics'!$C$5 | C21: =B21*'Executive Dashboard'!C17 | D21: =C21*'Executive Dashboard'!$D$27 | E21: =D21*'Executive Dashboard'!$D$28 | F21: =C21*'Executive Dashboard'!$D$31 | G21: =E21-F21 | H21: ='Single-Campus Pilot Economics'!$C$15/'Executive Dashboard'!$D$30 | I21: =G21-H21
A22: Month 2 | B22: ='Single-Campus Pilot Economics'!$C$5 | C22: =B22*'Executive Dashboard'!C17 | D22: =C22*'Executive Dashboard'!$D$27 | E22: =D22*'Executive Dashboard'!$D$28 | F22: =C22*'Executive Dashboard'!$D$31 | G22: =E22-F22 | H22: ='Single-Campus Pilot Economics'!$C$15/'Executive Dashboard'!$D$30 | I22: =G22-H22
A23: Month 3 | B23: ='Single-Campus Pilot Economics'!$C$5 | C23: =B23*'Executive Dashboard'!C17 | D23: =C23*'Executive Dashboard'!$D$27 | E23: =D23*'Executive Dashboard'!$D$28 | F23: =C23*'Executive Dashboard'!$D$31 | G23: =E23-F23 | H23: ='Single-Campus Pilot Economics'!$C$15/'Executive Dashboard'!$D$30 | I23: =G23-H23
A24: Month 4 | B24: ='Single-Campus Pilot Economics'!$C$5 | C24: =B24*'Executive Dashboard'!C17 | D24: =C24*'Executive Dashboard'!$D$27 | E24: =D24*'Executive Dashboard'!$D$28 | F24: =C24*'Executive Dashboard'!$D$31 | G24: =E24-F24 | H24: ='Single-Campus Pilot Economics'!$C$15/'Executive Dashboard'!$D$30 | I24: =G24-H24
A25: Month 5 | B25: ='Single-Campus Pilot Economics'!$C$5 | C25: =B25*'Executive Dashboard'!C17 | D25: =C25*'Executive Dashboard'!$D$27 | E25: =D25*'Executive Dashboard'!$D$28 | F25: =C25*'Executive Dashboard'!$D$31 | G25: =E25-F25 | H25: ='Single-Campus Pilot Economics'!$C$15/'Executive Dashboard'!$D$30 | I25: =G25-H25
A26: Month 6 | B26: ='Single-Campus Pilot Economics'!$C$5 | C26: =B26*'Executive Dashboard'!C17 | D26: =C26*'Executive Dashboard'!$D$27 | E26: =D26*'Executive Dashboard'!$D$28 | F26: =C26*'Executive Dashboard'!$D$31 | G26: =E26-F26 | H26: ='Single-Campus Pilot Economics'!$C$15/'Executive Dashboard'!$D$30 | I26: =G26-H26
A27: Month 7 | B27: ='Single-Campus Pilot Economics'!$C$5 | C27: =B27*'Executive Dashboard'!C17 | D27: =C27*'Executive Dashboard'!$D$27 | E27: =D27*'Executive Dashboard'!$D$28 | F27: =C27*'Executive Dashboard'!$D$31 | G27: =E27-F27 | H27: ='Single-Campus Pilot Economics'!$C$15/'Executive Dashboard'!$D$30 | I27: =G27-H27
A28: Month 8 | B28: ='Single-Campus Pilot Economics'!$C$5 | C28: =B28*'Executive Dashboard'!C17 | D28: =C28*'Executive Dashboard'!$D$27 | E28: =D28*'Executive Dashboard'!$D$28 | F28: =C28*'Executive Dashboard'!$D$31 | G28: =E28-F28 | H28: ='Single-Campus Pilot Economics'!$C$15/'Executive Dashboard'!$D$30 | I28: =G28-H28
A29: Month 9 | B29: ='Single-Campus Pilot Economics'!$C$5 | C29: =B29*'Executive Dashboard'!C17 | D29: =C29*'Executive Dashboard'!$D$27 | E29: =D29*'Executive Dashboard'!$D$28 | F29: =C29*'Executive Dashboard'!$D$31 | G29: =E29-F29 | H29: ='Single-Campus Pilot Economics'!$C$15/'Executive Dashboard'!$D$30 | I29: =G29-H29
A30: Month 10 | B30: ='Single-Campus Pilot Economics'!$C$5 | C30: =B30*'Executive Dashboard'!C17 | D30: =C30*'Executive Dashboard'!$D$27 | E30: =D30*'Executive Dashboard'!$D$28 | F30: =C30*'Executive Dashboard'!$D$31 | G30: =E30-F30 | H30: ='Single-Campus Pilot Economics'!$C$15/'Executive Dashboard'!$D$30 | I30: =G30-H30
A31: Month 11 | B31: ='Single-Campus Pilot Economics'!$C$5 | C31: =B31*'Executive Dashboard'!C17 | D31: =C31*'Executive Dashboard'!$D$27 | E31: =D31*'Executive Dashboard'!$D$28 | F31: =C31*'Executive Dashboard'!$D$31 | G31: =E31-F31 | H31: ='Single-Campus Pilot Economics'!$C$15/'Executive Dashboard'!$D$30 | I31: =G31-H31
A32: Month 12 | B32: ='Single-Campus Pilot Economics'!$C$5 | C32: =B32*'Executive Dashboard'!C17 | D32: =C32*'Executive Dashboard'!$D$27 | E32: =D32*'Executive Dashboard'!$D$28 | F32: =C32*'Executive Dashboard'!$D$31 | G32: =E32-F32 | H32: ='Single-Campus Pilot Economics'!$C$15/'Executive Dashboard'!$D$30 | I32: =G32-H32
A33: FULL YEAR TOTAL | B33: - | C33: =SUM(C21:C32) | D33: =SUM(D21:D32) | E33: =SUM(E21:E32) | F33: =SUM(F21:F32) | G33: =SUM(G21:G32) | H33: =SUM(H21:H32) | I33: =SUM(I21:I32)

Sheet 5-Year Growth Projections
A1: FoodLine Campus — 5-Year Growth Projections & Scale Model (Slide 11)
A2: Expansion across Campuses (4% Student Model) — Target Achieved in Year 5!
A4: Metric | B4: Derivation / Basis | C4: Year 1 | D4: Year 2 | E4: Year 3 | F4: Year 4 | G4: Year 5 | H4: 5-Year Cumulative / CAGR
A5: Active Campuses | B5: Target expansion campuses | C5: ='Executive Dashboard'!C14 | D5: ='Executive Dashboard'!D14 | E5: ='Executive Dashboard'!E14 | F5: ='Executive Dashboard'!F14 | G5: ='Executive Dashboard'!G14 | H5: =(G5/C5)^(1/4)-1
A6: Student Adoption Rate % | B6: Penetration of campus student body | C6: ='Executive Dashboard'!C15 | D6: ='Executive Dashboard'!D15 | E6: ='Executive Dashboard'!E15 | F6: ='Executive Dashboard'!F15 | G6: ='Executive Dashboard'!G15 | H6: =AVERAGE(C6:G6)
A7: Active Students | B7: Campuses * Students/Campus * Adoption % | C7: ='Executive Dashboard'!C16 | D7: ='Executive Dashboard'!D16 | E7: ='Executive Dashboard'!E16 | F7: ='Executive Dashboard'!F16 | G7: ='Executive Dashboard'!G16 | H7: =(G7/C7)^(1/4)-1
A8: Monthly Orders / Student | B8: Monthly order frequency per student | C8: ='Executive Dashboard'!C17 | D8: ='Executive Dashboard'!D17 | E8: ='Executive Dashboard'!E17 | F8: ='Executive Dashboard'!F17 | G8: ='Executive Dashboard'!G17 | H8: =AVERAGE(C8:G8)
A9: Annual Orders | B9: Active Students * Monthly Orders * Operating Months | C9: ='Executive Dashboard'!C18 | D9: ='Executive Dashboard'!D18 | E9: ='Executive Dashboard'!E18 | F9: ='Executive Dashboard'!F18 | G9: ='Executive Dashboard'!G18 | H9: =SUM(C9:G9)
A10: Annual GMV | B10: Annual Orders * AOV | C10: ='Executive Dashboard'!C19 | D10: ='Executive Dashboard'!D19 | E10: ='Executive Dashboard'!E19 | F10: ='Executive Dashboard'!F19 | G10: ='Executive Dashboard'!G19 | H10: =SUM(C10:G10)
A11: Revenue (4% Fee) | B11: Annual GMV * Convenience Fee % | C11: ='Executive Dashboard'!C20 | D11: ='Executive Dashboard'!D20 | E11: ='Executive Dashboard'!E20 | F11: ='Executive Dashboard'!F20 | G11: ='Executive Dashboard'!G20 | H11: =SUM(C11:G11)
A12: Lean Annual OPEX | B12: Executive Dashboard OPEX | C12: ='Executive Dashboard'!C21 | D12: ='Executive Dashboard'!D21 | E12: ='Executive Dashboard'!E21 | F12: ='Executive Dashboard'!F21 | G12: ='Executive Dashboard'!G21 | H12: =SUM(C12:G12)
A13: Direct Variable Tech Cost | B13: Annual Orders * Variable Tech Cost | C13: =C9*'Executive Dashboard'!$D$31 | D13: =D9*'Executive Dashboard'!$D$31 | E13: =E9*'Executive Dashboard'!$D$31 | F13: =F9*'Executive Dashboard'!$D$31 | G13: =G9*'Executive Dashboard'!$D$31 | H13: =SUM(C13:G13)
A14: NET ANNUAL PROFIT | B14: Revenue - (Lean OPEX + Variable Tech Cost) | C14: ='Executive Dashboard'!C22 | D14: ='Executive Dashboard'!D22 | E14: ='Executive Dashboard'!E22 | F14: ='Executive Dashboard'!F22 | G14: ='Executive Dashboard'!G22 | H14: =SUM(C14:G14)
A15: Net Profit Margin % | B15: Net Profit / Revenue | C15: ='Executive Dashboard'!C23 | D15: ='Executive Dashboard'!D23 | E15: ='Executive Dashboard'!E23 | F15: ='Executive Dashboard'!F23 | G15: ='Executive Dashboard'!G23 | H15: =H14/H11
A16: Year-over-Year Growth % | B16: Revenue YoY Growth | C16: - | D16: =(D11-C11)/C11 | E16: =(E11-D11)/D11 | F16: =(F11-E11)/E11 | G16: =(G11-F11)/F11 | H16: =(G11/C11)^(1/4)-1

Sheet Capital Requirements
A1: FoodLine Campus — Setup Cost & Initial Investment (Slide 9)
A2: Itemized capital requirements, funding allocation, and equity structure
A4: INITIAL CAPITAL ALLOCATION (SLIDE 9 TABLE)
A5: Expense Item | B5: Purpose / Allocation Details | C5: Amount (₹) [EDITABLE] | D5: % of Capital | E5: Vendor / Milestone
A6: Software Platform Build & Testing | B6: Next.js 15 PWA, real-time KDS & cloud infrastructure setup | C6: 60000 | D6: =C6/$C$11 | E6: Full-stack development, real-time SSE stream & UTR verification engine
A7: Canteen Hardware Setup | B7: 10" Android tablet + soundbox device for canteen kitchen | C7: 15000 | D7: =C7/$C$11 | E7: Rugged 10" Android tablet + Bluetooth soundbox for incoming order chime
A8: Company Registration & Legal | B8: Pvt Ltd incorporation, GST registration, and legal agreements | C8: 25000 | D8: =C8/$C$11 | E8: Ministry of Corporate Affairs (MCA), trademark, merchant MOU agreements
A9: Branding & Campus Signage | B9: QR code table tents for 50 tables + express counter banner | C9: 20000 | D9: =C9/$C$11 | E9: Acrylic table QR stands, express pickup counter vinyl branding & banners
A10: Working Capital Reserve | B10: Cash buffer for Year 1 cloud hosting & operations reserve | C10: 84000 | D10: =C10/$C$11 | E10: 14 months of cloud hosting (Supabase, AWS) and contingency buffer
A11: TOTAL INITIAL INVESTMENT REQUIRED | B11: 51% Founders Equity + 49% Seed Capital | C11: =SUM(C6:C10) | D11: =SUM(D6:D10) | E11: 100% Fully funded at launch
A14: CAPITAL STRUCTURE & OWNERSHIP SPLIT
A15: Funding Source | B15: Investor / Contributor | C15: Amount (₹) | D15: Equity % | E15: Terms & Rights
A16: Founders Equity | B16: Shivam Nirmal & Founding Team | C16: =$C$11*D16 | D16: ='Executive Dashboard'!$G$30 | E16: Controlling stake, operational leadership & board control
A17: Seed Capital / Incubation Grant | B17: SCILL / Seed Investor | C17: =$C$11*D17 | D17: ='Executive Dashboard'!$G$31 | E17: Seed incubation capital, advisory support & mentor network
A18: TOTAL CAPITAL POOL | B18: Combined Initial Capital | C18: =C16+C17 | D18: =D16+D17 | E18: 18-Month operational runway with zero cash burning

Sheet Viability Math & Break-Even
A1: FoodLine Campus — Break-Even Point & Payback Period (Slide 10)
A2: Mathematical viability, order thresholds, capacity cushions, and capital payback
A4: 1. BREAK-EVEN ANALYSIS MATH (SLIDE 10)
A5: Viability Metric | B5: Formula / Derivation | C5: Value | D5: Unit | E5: Strategic Context
A6: Annual Fixed OPEX | B6: Executive Dashboard Year 1 OPEX | C6: ='Executive Dashboard'!C21 | D6: ₹/Year | E6: Hosting + Campus Lead + Marketing
A7: Monthly Fixed OPEX | B7: Annual OPEX / 12 | C7: =C6/'Executive Dashboard'!$D$30 | D7: ₹/Month | E7: Extremely lean monthly burn rate
A8: Average Order Value (AOV) | B8: Executive Dashboard AOV | C8: ='Executive Dashboard'!$D$27 | D8: ₹/Order | E8: Snack + Beverage combo average ticket size
A9: Student Convenience Fee Rate | B9: AOV * Fee % | C9: =C8*'Executive Dashboard'!$D$28 | D9: ₹/Order | E9: Gross platform revenue collected per order
A10: Direct Variable Tech Cost per Order | B10: Executive Dashboard Tech Cost | C10: ='Executive Dashboard'!$D$31 | D10: ₹/Order | E10: SMS OTP, Supabase real-time SSE stream
A11: Net Contribution Margin per Order | B11: Revenue/Order - Tech Cost/Order | C11: =C9-C10 | D11: ₹/Order | E11: Net cash generated by every single order
A12: Contribution Margin Ratio | B12: Contribution Margin / Revenue | C12: =C11/C9 | D12: % | E12: Contribution Margin on revenue
A13: ANNUAL BREAK-EVEN ORDER VOLUME | B13: Annual Fixed OPEX / Contribution Margin | C13: =IF(C11>0, C6/C11, 0) | D13: Orders/Year | E13: Fixed costs ÷ Contribution Margin
A14: MONTHLY BREAK-EVEN ORDERS | B14: Annual Break-Even Orders / 12 | C14: =C13/'Executive Dashboard'!$D$30 | D14: Orders/Mo | E14: Monthly break-even order volume
A15: DAILY BREAK-EVEN ORDERS | B15: Monthly Orders / 25 Operating Days | C15: =C14/25 | D15: Orders/Day | E15: Assumes 25 operating days/month
A16: Projected Pilot Annual Orders | B16: Single-Campus Pilot Volume | C16: ='Single-Campus Pilot Economics'!$D$5 | D16: Orders/Year | E16: Modeled pilot volume
A17: Capacity Cushion / Break-Even % | B17: Break-Even Orders / Projected Orders | C17: =IF(C16>0, C13/C16, 0) | D17: % | E17: % of pilot volume needed to break even
A18: SAFETY MARGIN | B18: 1 - Capacity Cushion | C18: =1-C17 | D18: % | E18: Safety buffer above break-even point
A21: 2. ESTIMATED PAYBACK PERIOD & FINANCIAL VIABILITY (SLIDE 10)
A22: Payback Milestone | B22: Calculation Formula | C22: Timeline | D22: Status | E22: Operational Justification
A23: Hardware Tablet Payback | B23: Tablet Cost (₹15,000) / Monthly Profit | C23: < 45 Days | D23: Ultra-Rapid | E23: The ₹15,000 kitchen tablet cost is covered within 45 days of live orders
A24: Operational Break-Even | B24: Fixed OPEX covered by monthly contribution margin | C24: Month 1 | D24: Target Achieved | E24: Immediate operating profitability due to zero merchant churn and direct UPI
A25: Full Capital Payback | B25: Total Capital (₹2,04,000) / Monthly Profit | C25: < 4 Months | D25: Super-Fast | E25: Entire ₹2.04 Lakhs initial setup investment recovered in less than 4 months
A26: Canteen Churn Rate | B26: 0% Commission Model | C26: 0.0% | D26: Zero Churn | E26: Because canteens pay ₹0 commission, zero canteens churn or cancel
A27: Cash Flow Settlement | B27: Direct UPI Bank Rail | C27: Same-Day (T+0) | D27: Instant Liquidity | E27: Direct UPI routing ensures same-day settlement with zero debt or credit risk
A30: 3. SENSITIVITY MATRIX: ANNUAL REVENUE PER CAMPUS (AOV vs CONVENIENCE FEE %)
A31: AOV \ Fee Rate | B31: 0.03 | C31: 0.035 | D31: 0.04 | E31: 0.045 | F31: 0.05
A32: 50 | B32: ='Single-Campus Pilot Economics'!$D$5*A32*B31 | C32: ='Single-Campus Pilot Economics'!$D$5*A32*C31 | D32: ='Single-Campus Pilot Economics'!$D$5*A32*D31 | E32: ='Single-Campus Pilot Economics'!$D$5*A32*E31 | F32: ='Single-Campus Pilot Economics'!$D$5*A32*F31
A33: 60 | B33: ='Single-Campus Pilot Economics'!$D$5*A33*B31 | C33: ='Single-Campus Pilot Economics'!$D$5*A33*C31 | D33: ='Single-Campus Pilot Economics'!$D$5*A33*D31 | E33: ='Single-Campus Pilot Economics'!$D$5*A33*E31 | F33: ='Single-Campus Pilot Economics'!$D$5*A33*F31
A34: 70 | B34: ='Single-Campus Pilot Economics'!$D$5*A34*B31 | C34: ='Single-Campus Pilot Economics'!$D$5*A34*C31 | D34: ='Single-Campus Pilot Economics'!$D$5*A34*D31 | E34: ='Single-Campus Pilot Economics'!$D$5*A34*E31 | F34: ='Single-Campus Pilot Economics'!$D$5*A34*F31
A35: 80 | B35: ='Single-Campus Pilot Economics'!$D$5*A35*B31 | C35: ='Single-Campus Pilot Economics'!$D$5*A35*C31 | D35: ='Single-Campus Pilot Economics'!$D$5*A35*D31 | E35: ='Single-Campus Pilot Economics'!$D$5*A35*E31 | F35: ='Single-Campus Pilot Economics'!$D$5*A35*F31
A36: 90 | B36: ='Single-Campus Pilot Economics'!$D$5*A36*B31 | C36: ='Single-Campus Pilot Economics'!$D$5*A36*C31 | D36: ='Single-Campus Pilot Economics'!$D$5*A36*D31 | E36: ='Single-Campus Pilot Economics'!$D$5*A36*E31 | F36: ='Single-Campus Pilot Economics'!$D$5*A36*F31
A37: 100 | B37: ='Single-Campus Pilot Economics'!$D$5*A37*B31 | C37: ='Single-Campus Pilot Economics'!$D$5*A37*C31 | D37: ='Single-Campus Pilot Economics'!$D$5*A37*D31 | E37: ='Single-Campus Pilot Economics'!$D$5*A37*E31 | F37: ='Single-Campus Pilot Economics'!$D$5*A37*F31
A39: * Highlighted cell represents user's active baseline: ₹70 AOV and 4% Fee.

Sheet Goldmine Target (500 Campuses)
A1: FoodLine Campus — ₹25.00 Cr Goldmine Milestone & 5% Target Model
A2: User Defined: ₹25,00,00,000 GM Milestone Valuation | 5% Target = ₹1,25,00,000 (Achieved in Year 5!)
A4: 1. REVISED GOLDMINE 5% TARGET & 5-YEAR ACHIEVEMENT SUMMARY
A5: Goldmine Parameter | B5: Model Derivation | C5: Value | D5: Unit | E5: Strategic Basis & Status
A6: Total Goldmine (GM) Milestone Valuation | B6: Executive Dashboard Control | C6: ='Executive Dashboard'!$G$33 | D6: ₹ | E6: ₹25,00,00,000 (₹25.00 Crores) Total Target Milestone
A7: Goldmine Target Allocation % | B7: Executive Dashboard Control | C7: ='Executive Dashboard'!$G$34 | D7: % | E7: 5.0% Target Allocation requested by user
A8: TARGET GOLDMINE 5% CAPITALIZATION | B8: Valuation * Target % | C8: ='Executive Dashboard'!$G$35 | D8: ₹ | E8: ₹1,25,00,00,000 (₹1.25 Crores) — Target to Achieve
A9: Year 5 Net Annual Profit Achieved | B9: Executive Dashboard Year 5 Net Profit | C9: ='Executive Dashboard'!$G$22 | D9: ₹/Year | E9: ₹1,35,00,000 (₹1.35 Crores) generated in Year 5
A10: 5-YEAR TARGET ACHIEVEMENT RATE | B10: Year 5 Profit / Target Amount | C10: =C9/C8 | D10: % | E10: 108.0% OF TARGET ACHIEVED IN YEAR 5! (EXCEEDED BY ₹10 LAKHS)
A11: 5-Year Cumulative Net Profit Generated | B11: Sum of Years 1-5 Profit | C11: ='Executive Dashboard'!H22 | D11: ₹ | E11: ₹3,80,24,999 (~₹3.80 Crores) cumulative earnings
A12: CUMULATIVE 5-YEAR ACHIEVEMENT RATE | B12: Cumulative Profit / Target Amount | C12: =C11/C8 | D12: % | E12: 304.2% OF TARGET ACHIEVED CUMULATIVELY ACROSS 5 YEARS!
A13: Year 5 Operational Campuses | B13: Executive Dashboard Year 5 Campuses | C13: ='Executive Dashboard'!G14 | D13: Campuses | E13: 20 Campuses in Year 5
A14: Year 5 Active Dining Students | B14: Executive Dashboard Year 5 Students | C14: ='Executive Dashboard'!G16 | D14: Students | E14: 30,000 Active Dining Students across 20 Campuses
A15: Year 5 Annual Food Orders | B15: Executive Dashboard Year 5 Orders | C15: ='Executive Dashboard'!G18 | D15: Orders/Year | E15: 54,00,000 Digital Orders processed annually
A16: Year 5 Gross Food Volume (GMV) | B16: Executive Dashboard Year 5 GMV | C16: ='Executive Dashboard'!G19 | D16: ₹/Year | E16: ₹37,80,00,000 (₹37.80 Crores) annual food GMV
A17: Year 5 FoodLine Revenue (4% Fee) | B17: Executive Dashboard Year 5 Revenue | C17: ='Executive Dashboard'!G20 | D17: ₹/Year | E17: ₹1,51,20,000 (₹1.51 Crores) annual revenue
A20: 2. YEAR-BY-YEAR TARGET PROGRESSION TOWARD ₹1.25 CR (5% OF ₹25 CR)
A21: Year | B21: Campuses | C21: Active Students | D21: Annual Orders | E21: GMV (₹) | F21: Revenue (4%) | G21: Net Profit (₹) | H21: % of ₹1.25 Cr Target | I21: Achievement Status
A22: Year 1 | B22: ='Executive Dashboard'!C14 | C22: ='Executive Dashboard'!C16 | D22: ='Executive Dashboard'!C18 | E22: ='Executive Dashboard'!C19 | F22: ='Executive Dashboard'!C20 | G22: ='Executive Dashboard'!C22 | H22: =G22/$C$8 | I22: Scaling (18%)
A23: Year 2 | B23: ='Executive Dashboard'!D14 | C23: ='Executive Dashboard'!D16 | D23: ='Executive Dashboard'!D18 | E23: ='Executive Dashboard'!D19 | F23: ='Executive Dashboard'!D20 | G23: ='Executive Dashboard'!D22 | H23: =G23/$C$8 | I23: Scaling (36%)
A24: Year 3 | B24: ='Executive Dashboard'!E14 | C24: ='Executive Dashboard'!E16 | D24: ='Executive Dashboard'!E18 | E24: ='Executive Dashboard'!E19 | F24: ='Executive Dashboard'!E20 | G24: ='Executive Dashboard'!E22 | H24: =G24/$C$8 | I24: Scaling (54%)
A25: Year 4 | B25: ='Executive Dashboard'!F14 | C25: ='Executive Dashboard'!F16 | D25: ='Executive Dashboard'!F18 | E25: ='Executive Dashboard'!F19 | F25: ='Executive Dashboard'!F20 | G25: ='Executive Dashboard'!F22 | H25: =G25/$C$8 | I25: Near Target (81%)
A26: Year 5 | B26: ='Executive Dashboard'!G14 | C26: ='Executive Dashboard'!G16 | D26: ='Executive Dashboard'!G18 | E26: ='Executive Dashboard'!G19 | F26: ='Executive Dashboard'!G20 | G26: ='Executive Dashboard'!G22 | H26: =G26/$C$8 | I26: Target Achieved & Exceeded!
A27: 5-YEAR TOTAL | B27: - | C27: - | D27: =SUM(D22:D26) | E27: =SUM(E22:E26) | F27: =SUM(F22:F26) | G27: =SUM(G22:G26) | H27: =G27/$C$8 | I27: 304.2% CUMULATIVE RETURN!
